graph_3d_widget/__init__.py
graph_3d_widget/dev.py
graph_3d_widget/static/widget.css
graph_3d_widget/static/widget.js
graph_3d_widget-0.0.2.dist-info/METADATA
graph_3d_widget-0.0.2.dist-info/WHEEL
graph_3d_widget-0.0.2.dist-info/RECORD
