Metadata-Version: 2.4
Name: graph_3d_widget
Version: 0.0.2
Requires-Dist: anywidget
Requires-Dist: marimo
